cxflow_rethinkdb/__init__.py
cxflow_rethinkdb/rethinkdb_hook.py
cxflow_rethinkdb-0.1.1.dist-info/DESCRIPTION.rst
cxflow_rethinkdb-0.1.1.dist-info/METADATA
cxflow_rethinkdb-0.1.1.dist-info/RECORD
cxflow_rethinkdb-0.1.1.dist-info/WHEEL
cxflow_rethinkdb-0.1.1.dist-info/metadata.json
cxflow_rethinkdb-0.1.1.dist-info/top_level.txt
