Metadata-Version: 2.0
Name: cxflow-rethinkdb
Version: 0.1.1
Summary: RethinkDB plugin for cxflow
Home-page: https://gitlab.com/Cognexa/cxflow-rethinkdb
Author: Cognexa Solutions s.r.o.
Author-email: info@cognexa.com
License: MIT
Keywords: rethinkdb database cxflow
Platform: UNKNOWN
Classifier: Development Status :: 4 - Beta
Classifier: Environment :: Console
Classifier: Intended Audience :: Developers
Classifier: Intended Audience :: Education
Classifier: Intended Audience :: Science/Research
Classifier: Operating System :: Unix
Classifier: Programming Language :: Python :: Implementation :: CPython
Classifier: Topic :: Scientific/Engineering :: Artificial Intelligence
Classifier: License :: OSI Approved :: MIT License
Classifier: Programming Language :: Python :: 3.5
Classifier: Programming Language :: Python :: 3.6
Requires-Dist: cxflow (>=0.7.0)
Requires-Dist: numpy (>=1.13.0)
Requires-Dist: pip (>=9.0.0)
Requires-Dist: pyaml (>=16.12.2)
Requires-Dist: pytz (>=2017.2)
Requires-Dist: rethinkdb (>=2.3.0)
Requires-Dist: typing (>=3.5.3.0)
